hydesign/Parallel_EGO.py
hydesign/__init__.py
hydesign/_version.py
hydesign/battery_degradation.py
hydesign/nrel_csm_wrapper.py
hydesign/openmdao_wrapper.py
hydesign/reliability.py
hydesign/reliability_utils.py
hydesign/utils.py
hydesign/HiFiEMS/DEMS.py
hydesign/HiFiEMS/Deg_Calculation.py
hydesign/HiFiEMS/__init__.py
hydesign/HiFiEMS/run.py
hydesign/HiFiEMS/utils.py
hydesign/assembly/__init__.py
hydesign/assembly/hpp_assembly.py
hydesign/assembly/hpp_assembly_BM.py
hydesign/assembly/hpp_assembly_P2X.py
hydesign/assembly/hpp_assembly_P2X_bidrectional.py
hydesign/assembly/hpp_assembly_constantoutput.py
hydesign/assembly/hpp_assembly_hifi_dems.py
hydesign/assembly/hpp_assembly_hybridization_pv.py
hydesign/assembly/hpp_assembly_hybridization_wind.py
hydesign/assembly/hpp_assembly_reliability.py
hydesign/assembly/hpp_assembly_solarX.py
hydesign/assembly/hpp_pywake.py
hydesign/assembly/hpp_pywake_p2x.py
hydesign/assembly/hpp_pywake_p2x_pod.py
hydesign/costs/__init__.py
hydesign/costs/costs.py
hydesign/costs/costs_hybridized_pv.py
hydesign/costs/costs_hybridized_wind.py
hydesign/costs/costs_solarX.py
hydesign/cpv/__init__.py
hydesign/cpv/cpv.py
hydesign/cst/__init__.py
hydesign/cst/cst.py
hydesign/ems/EmsSolarX.py
hydesign/ems/__init__.py
hydesign/ems/ems.py
hydesign/ems/ems_BM.py
hydesign/ems/ems_P2X.py
hydesign/ems/ems_P2X_bidirectional.py
hydesign/ems/ems_constant_output.py
hydesign/ems/ems_hifi_dems.py
hydesign/examples/__init__.py
hydesign/examples/examples_sites.csv
hydesign/examples/Europe/2030-EL_PRICE.csv
hydesign/examples/Europe/Electrolyzer_efficiency_curves.csv
hydesign/examples/Europe/H2_demand.csv
hydesign/examples/Europe/Inverter_efficiency_curves.csv
hydesign/examples/Europe/__init__.py
hydesign/examples/Europe/hpp_pars.yml
hydesign/examples/Europe/hpp_pars_HiFiEMS.yml
hydesign/examples/Europe/hpp_pars_Hjortmose.yml
hydesign/examples/Europe/hpp_pars_Langelinie.yml
hydesign/examples/Europe/hpp_pars_benchmark.yml
hydesign/examples/Europe/hpp_pars_gwa3.yml
hydesign-1.6.0.dist-info/licenses/LICENSE
hydesign-1.6.0.dist-info/METADATA
hydesign-1.6.0.dist-info/WHEEL
hydesign-1.6.0.dist-info/top_level.txt
hydesign-1.6.0.dist-info/zip-safe
hydesign-1.6.0.dist-info/RECORD
