Metadata-Version: 2.4
Name: hydesign
Version: 1.6.0
Summary: A tool for design and control of utility-scale wind-solar-storage based hybrid power plant.
Author-email: DTU Wind Energy <mikf@dtu.dk>
License: MIT
Project-URL: Documentation, https://topfarm.pages.windenergy.dtu.dk/hydesign/
Project-URL: Source, https://gitlab.windenergy.dtu.dk/TOPFARM/hydesign
Project-URL: Tracker, https://gitlab.windenergy.dtu.dk/TOPFARM/hydesign/-/issues
Requires-Python: >=3.9
License-File: LICENSE
Requires-Dist: numpy>=2
Requires-Dist: pandas
Requires-Dist: scipy
Requires-Dist: h5netcdf
Requires-Dist: netcdf4
Requires-Dist: xarray
Requires-Dist: openmdao
Requires-Dist: smt==2.9.2
Requires-Dist: cplex
Requires-Dist: docplex
Requires-Dist: numpy-financial
Requires-Dist: pvlib
Requires-Dist: statsmodels
Requires-Dist: rainflow
Requires-Dist: pyyaml
Requires-Dist: matplotlib
Requires-Dist: ortools
Requires-Dist: NREL-PySAM
Requires-Dist: tqdm
Requires-Dist: h5py>=3.13
Provides-Extra: all
Requires-Dist: hydesign[docs,loads,reliability,test]; extra == "all"
Provides-Extra: test
Requires-Dist: pre-commit; extra == "test"
Requires-Dist: pytest; extra == "test"
Requires-Dist: pytest-cov; extra == "test"
Provides-Extra: optional
Requires-Dist: seaborn; extra == "optional"
Requires-Dist: jupyterlab; extra == "optional"
Requires-Dist: finitediff; extra == "optional"
Requires-Dist: dask; extra == "optional"
Requires-Dist: scikit-learn; extra == "optional"
Requires-Dist: zarr; extra == "optional"
Requires-Dist: openpyxl; extra == "optional"
Provides-Extra: docs
Requires-Dist: pypandoc; extra == "docs"
Requires-Dist: sphinx<=7.3.7; extra == "docs"
Requires-Dist: nbsphinx; extra == "docs"
Requires-Dist: nbconvert; extra == "docs"
Requires-Dist: sphinx_rtd_theme; extra == "docs"
Requires-Dist: sphinx-autoapi; extra == "docs"
Requires-Dist: sphinx-tags; extra == "docs"
Provides-Extra: loads
Requires-Dist: surrogates-interface; extra == "loads"
Requires-Dist: py_wake; extra == "loads"
Requires-Dist: topfarm; extra == "loads"
Provides-Extra: reliability
Requires-Dist: chaospy; extra == "reliability"
Dynamic: license-file
